gamenavigator/__init__.py
gamenavigator/config.py
gamenavigator/controller.py
gamenavigator/exception.py
gamenavigator/game_controller.py
gamenavigator/game_interface_controller.py
gamenavigator/image_recognition.py
gamenavigator/keyboard_mouse_simulation.py
gamenavigator/listener.py
gamenavigator/log.py
gamenavigator/ocr_recognition.py
gamenavigator/core/__init__.py
gamenavigator/core/image.py
gamenavigator/core/interface.py
gamenavigator/core/pos.py
gamenavigator/core/rect.py
GameWorldNavigator-0.0.7.8.dist-info/LICENSE
GameWorldNavigator-0.0.7.8.dist-info/METADATA
GameWorldNavigator-0.0.7.8.dist-info/WHEEL
GameWorldNavigator-0.0.7.8.dist-info/top_level.txt
GameWorldNavigator-0.0.7.8.dist-info/RECORD
