Metadata-Version: 2.1
Name: GameWorldNavigator
Version: 0.0.7.8
Summary: A framework for game automation
Home-page: https://github.com/JunNanLYS/GameWorldNavigator
Author: NanJunLYS
Author-email: 18906571516@163.com
Classifier: Programming Language :: Python :: 3
Classifier: License :: OSI Approved :: MIT License
Classifier: Operating System :: OS Independent
License-File: LICENSE
Requires-Dist: certifi (==2023.7.22)
Requires-Dist: charset-normalizer (==3.3.2)
Requires-Dist: coloredlogs (==15.0.1)
Requires-Dist: docutils (==0.20.1)
Requires-Dist: flatbuffers (==23.5.26)
Requires-Dist: humanfriendly (==10.0)
Requires-Dist: idna (==3.4)
Requires-Dist: importlib-metadata (==6.8.0)
Requires-Dist: jaraco.classes (==3.3.0)
Requires-Dist: keyring (==24.3.0)
Requires-Dist: markdown-it-py (==3.0.0)
Requires-Dist: mdurl (==0.1.2)
Requires-Dist: more-itertools (==10.1.0)
Requires-Dist: MouseInfo (==0.1.3)
Requires-Dist: mpmath (==1.3.0)
Requires-Dist: nh3 (==0.2.14)
Requires-Dist: numpy (==1.26.2)
Requires-Dist: onnxruntime (==1.16.2)
Requires-Dist: opencv-python (==4.8.1.78)
Requires-Dist: packaging (==23.2)
Requires-Dist: Pillow (==10.1.0)
Requires-Dist: pkginfo (==1.9.6)
Requires-Dist: ppocr-onnx (==0.0.3.9)
Requires-Dist: protobuf (==4.25.1)
Requires-Dist: PyAutoGUI (==0.9.54)
Requires-Dist: pyclipper (==1.3.0.post5)
Requires-Dist: PyGetWindow (==0.0.9)
Requires-Dist: Pygments (==2.16.1)
Requires-Dist: PyMsgBox (==1.0.9)
Requires-Dist: pynput (==1.7.6)
Requires-Dist: pyperclip (==1.8.2)
Requires-Dist: pyreadline3 (==3.4.1)
Requires-Dist: PyRect (==0.2.0)
Requires-Dist: PyScreeze (==0.1.30)
Requires-Dist: pytweening (==1.0.7)
Requires-Dist: pywin32 (==306)
Requires-Dist: pywin32-ctypes (==0.2.2)
Requires-Dist: readme-renderer (==42.0)
Requires-Dist: requests (==2.31.0)
Requires-Dist: requests-toolbelt (==1.0.0)
Requires-Dist: rfc3986 (==2.0.0)
Requires-Dist: rich (==13.7.0)
Requires-Dist: shapely (==2.0.2)
Requires-Dist: six (==1.16.0)
Requires-Dist: sympy (==1.12)
Requires-Dist: twine (==4.0.2)
Requires-Dist: urllib3 (==2.1.0)
Requires-Dist: zipp (==3.17.0)
